d1y/__init__.py
dylib-0.0.1.dist-info/METADATA
dylib-0.0.1.dist-info/WHEEL
dylib-0.0.1.dist-info/top_level.txt
dylib-0.0.1.dist-info/RECORD
